{
  "id": "cakovice",
  "name": "Čakovice",
  "type": "HAZARD_ZONE",
  "layout": {
    "0": "assets/maps_c/map_cakovice0.txt",
    "1": "assets/maps_c/map_cakovice1.txt"
  },
  "objects": [
  ],
  "tileTriggers": {
    "-": {
      "lineId": "line_c"
    }
  },
  "links": [
    {
      "from": "◄",
      "to": "▲"
    },
    {
      "from": "▲",
      "to": "◄"
    },
    {
      "from": "►",
      "to": "▼"
    },
    {
      "from": "▼",
      "to": "►"
    }
  ],
  "spawnMarkers": {
    "@": "line_c"
  }
}